{
  "date": "29-Jun-2026",
  "fii_buy": 24754.26,
  "fii_sell": 26104.36,
  "fii_net": -1350.1,
  "dii_buy": 55273.85,
  "dii_sell": 52472.4,
  "dii_net": 2801.45,
  "fii_idx_fut_long": 60489,
  "fii_idx_fut_short": 294940,
  "fii_idx_fut_net": -234451,
  "fii_idx_call_long": 871182,
  "fii_idx_call_short": 1263889,
  "fii_idx_call_net": -392707,
  "fii_idx_put_long": 1116554,
  "fii_idx_put_short": 647669,
  "fii_idx_put_net": 468885,
  "fii_pcr": 1.28,
  "fii_sentiment": "Bearish \ud83d\udc3b",
  "_updated_at": "29-Jun-2026 22:13 IST",
  "_source": "github-actions"
}