{
  "date": "24-Jun-2026",
  "fii_buy": 16744.73,
  "fii_sell": 18588.13,
  "fii_net": -1843.4,
  "dii_buy": 17274.01,
  "dii_sell": 13636.75,
  "dii_net": 3637.26,
  "fii_idx_fut_long": 46870,
  "fii_idx_fut_short": 275923,
  "fii_idx_fut_net": -229053,
  "fii_idx_call_long": 554506,
  "fii_idx_call_short": 1179334,
  "fii_idx_call_net": -624828,
  "fii_idx_put_long": 845271,
  "fii_idx_put_short": 575924,
  "fii_idx_put_net": 269347,
  "fii_pcr": 1.52,
  "fii_sentiment": "Bearish \ud83d\udc3b",
  "_updated_at": "24-Jun-2026 21:09 IST",
  "_source": "github-actions"
}